superset_sqlalchemy_gizmosql_adbc_dialect/__init__.py
superset_sqlalchemy_gizmosql_adbc_dialect/sqlalchemy_interfaces.py
superset_sqlalchemy_gizmosql_adbc_dialect-0.0.8.dist-info/licenses/LICENSE
superset_sqlalchemy_gizmosql_adbc_dialect-0.0.8.dist-info/METADATA
superset_sqlalchemy_gizmosql_adbc_dialect-0.0.8.dist-info/WHEEL
superset_sqlalchemy_gizmosql_adbc_dialect-0.0.8.dist-info/entry_points.txt
superset_sqlalchemy_gizmosql_adbc_dialect-0.0.8.dist-info/top_level.txt
superset_sqlalchemy_gizmosql_adbc_dialect-0.0.8.dist-info/RECORD
