Metadata-Version: 2.4
Name: superset-sqlalchemy-gizmosql-adbc-dialect
Version: 0.0.8
Summary: An Apache Superset compatible SQLAlchemy dialect for connecting to a [GizmoSQL](https://github.com/gizmodata/gizmosql) server with ADBC
Author-email: Philip Moore <philip@gizmodata.com>
License-Expression: Apache-2.0
Project-URL: Homepage, https://github.com/gizmodata/superset-sqlalchemy-gizmosql-adbc-dialect
Keywords: apache,superset,sqlalchemy,flight-sql,gizmosql,adbc,dialect
Classifier: Programming Language :: Python
Classifier: Programming Language :: Python :: 3
Requires-Python: >=3.10
License-File: LICENSE
Requires-Dist: apache-superset==5.0.*
Requires-Dist: adbc-driver-flightsql==1.8.*
Requires-Dist: psycopg2-binary==2.9.*
Requires-Dist: importlib-metadata==8.7.*
Provides-Extra: test
Requires-Dist: pytest; extra == "test"
Requires-Dist: pytest-snapshot; extra == "test"
Requires-Dist: pytest-mock; extra == "test"
Requires-Dist: filelock; extra == "test"
Requires-Dist: duckdb; extra == "test"
Requires-Dist: dask; extra == "test"
Requires-Dist: distributed; extra == "test"
Requires-Dist: pins[gcs]; extra == "test"
Requires-Dist: docker; extra == "test"
Provides-Extra: dev
Requires-Dist: bumpver; extra == "dev"
Requires-Dist: pip-tools; extra == "dev"
Requires-Dist: pytest; extra == "dev"
Dynamic: license-file
